pyDCAM/__init__.py
pyDCAM/_util.py
pyDCAM/dcamapi.py
pyDCAM/dcamapi_enum.py
pyDCAM/dcamapi_struct.py
pyDCAM/dcamprop.py
pyDCAM-0.0.1.dist-info/METADATA
pyDCAM-0.0.1.dist-info/WHEEL
pyDCAM-0.0.1.dist-info/top_level.txt
pyDCAM-0.0.1.dist-info/RECORD
