Metadata-Version: 2.1
Name: pyDCAM
Version: 0.0.1
Author-email: "Chung-You (Gilbert) Shih" <c5shih@uwaterloo.ca>
Project-URL: Source, https://github.com/QITI/Luxbeam
Project-URL: Homepage, https://github.com/QITI/Luxbeam
Requires-Dist: numpy >1
